<?xml version="1.0" encoding="UTF-8"?>
<LanguageData>
  
  <!-- EN: drone -->
  <Drone.label>无人机</Drone.label>
  
  <!-- EN: drone -->
  <DroneWithThreeLegs.label>无人机</DroneWithThreeLegs.label>
  <!-- EN: center leg -->
  <DroneWithThreeLegs.corePart.parts.center_leg.customLabel>中腿</DroneWithThreeLegs.corePart.parts.center_leg.customLabel>
  <!-- EN: rear left leg -->
  <DroneWithThreeLegs.corePart.parts.rear_left_leg.customLabel>左后腿</DroneWithThreeLegs.corePart.parts.rear_left_leg.customLabel>
  <!-- EN: rear right leg -->
  <DroneWithThreeLegs.corePart.parts.rear_right_leg.customLabel>右后腿</DroneWithThreeLegs.corePart.parts.rear_right_leg.customLabel>
  
  <!-- EN: drone -->
  <DroneWithTreads.label>无人机</DroneWithTreads.label>
  <!-- EN: front left tread -->
  <DroneWithTreads.corePart.parts.front_left_tread.customLabel>左前胎</DroneWithTreads.corePart.parts.front_left_tread.customLabel>
  <!-- EN: back left tread -->
  <DroneWithTreads.corePart.parts.back_left_tread.customLabel>左后胎</DroneWithTreads.corePart.parts.back_left_tread.customLabel>
  <!-- EN: front right tread -->
  <DroneWithTreads.corePart.parts.front_right_tread.customLabel>右前胎</DroneWithTreads.corePart.parts.front_right_tread.customLabel>
  <!-- EN: back right tread -->
  <DroneWithTreads.corePart.parts.back_right_tread.customLabel>右后胎</DroneWithTreads.corePart.parts.back_right_tread.customLabel>
  
</LanguageData>