<?xml version="1.0" encoding="UTF-8"?>
<LanguageData>

  <AccuracyTouch.label>精准度 (近身)</AccuracyTouch.label>
  <AccuracyTouch.description>在近身范围内的精准度倍率。</AccuracyTouch.description>

  <AccuracyShort.label>精准度 (近距离)</AccuracyShort.label>
  <AccuracyShort.description>在近距离范围内的精准度倍率。</AccuracyShort.description>

  <AccuracyMedium.label>精准度 (中距离)</AccuracyMedium.label>
  <AccuracyMedium.description>在中距离范围内的精准度倍率.</AccuracyMedium.description>

  <AccuracyLong.label>精准度 (远距离)</AccuracyLong.label>
  <AccuracyLong.description>在远距离范围内的精准度倍率.</AccuracyLong.description>

  <RangedWeapon_Cooldown.label>远程冷却</RangedWeapon_Cooldown.label>
  <RangedWeapon_Cooldown.description>在每次射击之后所需要的恢复时间。</RangedWeapon_Cooldown.description>

</LanguageData>
