<?xml version="1.0" encoding="UTF-8"?>
<LanguageData>
  
  <!-- EN: dancing. -->
  <Dance.reportString>TODO</Dance.reportString>
  
  <!-- EN: eating at TargetA. -->
  <EatAtCannibalPlatter.reportString>TODO</EatAtCannibalPlatter.reportString>
  
  <!-- EN: relaxing socially. -->
  <GotoAndBeSociallyActive.reportString>TODO</GotoAndBeSociallyActive.reportString>
  
  <!-- EN: making a skylantern. -->
  <PrepareSkylantern.reportString>TODO</PrepareSkylantern.reportString>
  
</LanguageData>