<?xml version="1.0" encoding="UTF-8"?>
<LanguageData>
  
  <!-- Misc -->
  <!-- EN: Need mechanitor colonist -->
  <MissingRequiredMechanitor>TODO</MissingRequiredMechanitor>
  <!-- EN: {0} not studied -->
  <NotStudied>TODO</NotStudied>
  <!-- EN: Requires study of -->
  <StudyRequirements>TODO</StudyRequirements>

  <!-- Work tab -->
  <!-- EN: {0_nameDef} is only {1} years old. {2} work can only be done from age {3} -->
  <WorkDisabledAge>TODO</WorkDisabledAge>
  <!-- EN: Click to change work mode. -->
  <ClickToChangeWorkMode>TODO</ClickToChangeWorkMode>


</LanguageData>