<?xml version="1.0" encoding="utf-8" ?>
<LanguageData>

  <NewColony>新殖民地</NewColony>
  <BackToGame>回到游戏</BackToGame>
  <Save>保存</Save>
  <Load>读取</Load>
  <Options>选项</Options>
  <Mods>Mod</Mods>
  <Credits>制作组</Credits>
  <QuitToMainMenu>返回主菜单</QuitToMainMenu>
  <QuitToOS>退出游戏</QuitToOS>
  <FictionPrimer>游戏背景</FictionPrimer>
  <LudeonBlog>Ludeon博客</LudeonBlog>
  <Forums>论坛</Forums>
  <OfficialWiki>官方百科</OfficialWiki>
  <TynansTwitter>Tynan的twitter</TynansTwitter>
  <TynansDesignBook>Tynan的设计指南书</TynansDesignBook>

  <GetMods>获取更多Mod</GetMods>
  <ConfirmDisableCoreMod>你确定要关闭Core(核心)模组吗？除非有完全替代游戏核心所有功能的模组，否则游戏将完全无法运行。\n\n记住，其它模组能通过使用同样的defName来覆盖游戏内的设定。</ConfirmDisableCoreMod>
  <Author>作者</Author>
  
  <Gameplay>Gameplay</Gameplay>

  <ChooseAIStoryteller>选择AI故事叙述者</ChooseAIStoryteller>
  
  <CreateCharacters>创建角色</CreateCharacters>

  <Start>开始</Start>
  <Advanced>高级</Advanced>
  <Next>继续</Next>
  <Back>返回</Back>

  <ConfirmQuit>确认退出吗？你将失去所有没保存的游戏进度。</ConfirmQuit>
  <EveryoneNeedsValidName>每个角色都需要一个有效的名字。</EveryoneNeedsValidName>

  <GeneratingWorld>生成世界中...</GeneratingWorld>

</LanguageData>