<?xml version="1.0" encoding="UTF-8"?>
<LanguageData>
  
  <!-- EN: ambush -->
  <Ambush.label>伏击</Ambush.label>
  <!-- EN: Caravan ambushed -->
  <Ambush.letterLabel>远行队遭遇伏击</Ambush.letterLabel>
  <!-- EN: {0} has been ambushed by {1} from {2}! -->
  <Ambush.letterText>{0}被来自{2}的{1}的伏击了！</Ambush.letterText>
  
  <!-- EN: payment demand -->
  <CaravanDemand.label>打劫</CaravanDemand.label>
  
  <!-- EN: caravan meeting -->
  <CaravanMeeting.label>远行队相遇</CaravanMeeting.label>
  
  <!-- EN: manhunter ambush -->
  <ManhunterAmbush.label>猎杀人类伏击</ManhunterAmbush.label>
  <!-- EN: Caravan ambushed (manhunters) -->
  <ManhunterAmbush.letterLabel>远行队遭遇伏击（猎杀人类）</ManhunterAmbush.letterLabel>
  <!-- EN: {0} has been ambushed by scaria-infected manhunting {1}! -->
  <ManhunterAmbush.letterText>{0}被感染了狂暴症的{1}伏击了！</ManhunterAmbush.letterText>
  
</LanguageData>