<?xml version="1.0" encoding="UTF-8"?>
<LanguageData>
  
  <!-- EN: got some lovin' -->
  <GotLovin.label>滚床单</GotLovin.label>
  
  <!-- EN: lovin' outside marriage -->
  <GotLovin_NonSpouse.label>婚外情</GotLovin_NonSpouse.label>
  
  <!-- EN: lovin' with spouse -->
  <GotLovin_Spouse.label>和配偶滚床单</GotLovin_Spouse.label>
  
  <!-- EN: initiated lovin' -->
  <InitiatedLovin.label>尝试滚床单</InitiatedLovin.label>
  
  <!-- EN: shared bed -->
  <SharedBed.label>一起睡</SharedBed.label>
  
  <!-- EN: shared bed outside marriage -->
  <SharedBed_NonSpouse.label>和情人一起睡</SharedBed_NonSpouse.label>
  
  <!-- EN: shared bed with spouse -->
  <SharedBed_Spouse.label>和配偶一起睡</SharedBed_Spouse.label>
  
</LanguageData>